MANIFEST.in
README.rst
setup.cfg
setup.py
gdflib/__init__.py
gdflib/node.py
gdflib/schema.py
gdflib.egg-info/PKG-INFO
gdflib.egg-info/SOURCES.txt
gdflib.egg-info/dependency_links.txt
gdflib.egg-info/entry_points.txt
gdflib.egg-info/not-zip-safe
gdflib.egg-info/top_level.txt