Metadata-Version: 1.0
Name: gdflib
Version: 0.0.1
Summary: Library to save graph GDF files
Home-page: https://github.com/amol-/gdflib
Author: Alessandro Molina
Author-email: alessandro.molina@axant.it
License: MIT
Platform: UNKNOWN
